[{
  "type": "input",
  "key": "name",
	"title": "请输入你的姓名",
	"category": "basic",
	"option": null
}, {
  "type": "selection",
  "key": "sex",
	"title": "你的性别",
	"category": "basic",
	"option": [{
    "score": "男",
		"degree": "男"
	}, {
    "score": "女",
		"degree": "女"
  }]
}, {
	"type": "date",
  "key": "birthday",
	"title": "请选择你的出生年月",
	"category": "basic",
	"option": null
}, {
	"type": "input",
  "key": "height",
	"title": "你的身高",
  "category": "basic",
  "extra": "厘米",
	"option": null
}, {
  "type": "input",
  "key": "weight",
  "title": "你的体重",
  "extra": "千克",
	"category": "basic",
	"option": null
}, {
  "type": "selection",
  "key": "education",
	"title": "文化水平",
	"category": "basic",
	"option": [{
    "score": "大专及以下",
		"degree": "大专及以下"
	}, {
    "score": "本科",
		"degree": "本科"
	}, {
    "score": "研究生及以上",
		"degree": "研究生及以上"
	}]
}, {
	"type": "selection",
  "key": "marriage",
	"title": "目前婚姻情况",
	"category": "basic",
	"option": [{
    "score": "已婚",
    "degree": "已婚"
	}, {
    "score": "离婚",
    "degree": "离婚"
	}, {
    "score": "丧偶",
    "degree": "丧偶"
	}, {
    "score": "未婚",
    "degree": "未婚"
	}]
}, {
	"type": "checkbox",
  "key": "degree",
	"title": "既往病史(多选)",
	"category": "basic",
	"option": [{
		"score": "高血压",
		"degree": "高血压"
	}, {
		"score": "高血脂",
		"degree": "高血脂"
	}, {
		"score": "糖尿病",
		"degree": "糖尿病"
	}, {
		"score": "冠心病家族史",
		"degree": "冠心病家族史"
	}, {
		"score": "脑血管疾病",
		"degree": "脑血管疾病"
	}, {
		"score": "慢性阻塞性肺病",
		"degree": "慢性阻塞性肺病"
	}, {
		"score": "骨骼系统疾病",
		"degree": "骨骼系统疾病"
	}, {
		"score": "其他脏器疾病",
		"degree": "其他脏器疾病"
	}]
}, {
  "type": "date",
  "key": "date",
	"title": "最后一次支架手术时间",
	"category": "basic",
	"option": null
}, {
	"type": "input",
  "key": "hospital",
	"title": "最后一次支架手术医院",
	"category": "basic",
	"option": null
}, {
	"id": 1,
	"type": "selection",
	"title": "过去1个月内，由于胸痛、胸部紧榨感和心绞痛所致自己穿衣的受限程度",
	"category": "survey",
	"key": "SAQ",
	"option": [{
		"degree": "重度受限",
		"score": 1
	}, {
		"degree": "中度受限",
		"score": 2
	}, {
		"degree": "轻度受限",
		"score": 3
	}, {
		"degree": "稍受限",
		"score": 4
	}, {
		"degree": "不受限",
		"score": 5
	}, {
		"degree": "因其它原因受限",
		"score": 6
	}]
}, {
	"id": 2,
	"type": "selection",
	"title": "过去1个月内，由于胸痛、胸部紧榨感和心绞痛所致室内走路的受限程度",
	"category": "survey",
	"key": "SAQ",
	"option": [{
		"degree": "重度受限",
		"score": 1
	}, {
		"degree": "中度受限",
		"score": 2
	}, {
		"degree": "轻度受限",
		"score": 3
	}, {
		"degree": "稍受限",
		"score": 4
	}, {
		"degree": "不受限",
		"score": 5
	}, {
		"degree": "因其它原因受限",
		"score": 6
	}]
}, {
	"id": 3,
	"type": "selection",
	"title": "过去1个月内，由于胸痛、胸部紧榨感和心绞痛所致淋浴的受限程度",
	"category": "survey",
	"key": "SAQ",
	"option": [{
		"degree": "重度受限",
		"score": 1
	}, {
		"degree": "中度受限",
		"score": 2
	}, {
		"degree": "轻度受限",
		"score": 3
	}, {
		"degree": "稍受限",
		"score": 4
	}, {
		"degree": "不受限",
		"score": 5
	}, {
		"degree": "因其它原因受限",
		"score": 6
	}]
}, {
	"id": 4,
	"type": "selection",
	"title": "过去1个月内，由于胸痛、胸部紧榨感和心绞痛所致爬坡或楼梯(三层且不停)的受限程度",
	"category": "survey",
	"key": "SAQ",
	"option": [{
		"degree": "重度受限",
		"score": 1
	}, {
		"degree": "中度受限",
		"score": 2
	}, {
		"degree": "轻度受限",
		"score": 3
	}, {
		"degree": "稍受限",
		"score": 4
	}, {
		"degree": "不受限",
		"score": 5
	}, {
		"degree": "因其它原因受限",
		"score": 6
	}]
}, {
	"id": 5,
	"type": "selection",
	"title": "过去1个月内，由于胸痛、胸部紧榨感和心绞痛所致户外活动或提杂物的受限程度",
	"category": "survey",
	"key": "SAQ",
	"option": [{
		"degree": "重度受限",
		"score": 1
	}, {
		"degree": "中度受限",
		"score": 2
	}, {
		"degree": "轻度受限",
		"score": 3
	}, {
		"degree": "稍受限",
		"score": 4
	}, {
		"degree": "不受限",
		"score": 5
	}, {
		"degree": "因其它原因受限",
		"score": 6
	}]
}, {
	"id": 6,
	"type": "selection",
	"title": "过去1个月内，由于胸痛、胸部紧榨感和心绞痛所致轻快步行一段路(一公里)的受限程度",
	"category": "survey",
	"key": "SAQ",
	"option": [{
		"degree": "重度受限",
		"score": 1
	}, {
		"degree": "中度受限",
		"score": 2
	}, {
		"degree": "轻度受限",
		"score": 3
	}, {
		"degree": "稍受限",
		"score": 4
	}, {
		"degree": "不受限",
		"score": 5
	}, {
		"degree": "因其它原因受限",
		"score": 6
	}]
}, {
	"id": 7,
	"type": "selection",
	"title": "过去1个月内，由于胸痛、胸部紧榨感和心绞痛所致慢跑(一公里)的受限程度",
	"category": "survey",
	"key": "SAQ",
	"option": [{
		"degree": "重度受限",
		"score": 1
	}, {
		"degree": "中度受限",
		"score": 2
	}, {
		"degree": "轻度受限",
		"score": 3
	}, {
		"degree": "稍受限",
		"score": 4
	}, {
		"degree": "不受限",
		"score": 5
	}, {
		"degree": "因其它原因受限",
		"score": 6
	}]
}, {
	"id": 8,
	"type": "selection",
	"title": "过去1个月内，由于胸痛、胸部紧榨感和心绞痛所致提起或移动重物的受限程度",
	"category": "survey",
	"key": "SAQ",
	"option": [{
		"degree": "重度受限",
		"score": 1
	}, {
		"degree": "中度受限",
		"score": 2
	}, {
		"degree": "轻度受限",
		"score": 3
	}, {
		"degree": "稍受限",
		"score": 4
	}, {
		"degree": "不受限",
		"score": 5
	}, {
		"degree": "因其它原因受限",
		"score": 6
	}]
}, {
	"id": 9,
	"type": "selection",
	"title": "过去1个月内，由于胸痛、胸部紧榨感和心绞痛所致剧烈运动(如游泳或打球)的受限程度",
	"category": "survey",
	"key": "SAQ",
	"option": [{
		"degree": "重度受限",
		"score": 1
	}, {
		"degree": "中度受限",
		"score": 2
	}, {
		"degree": "轻度受限",
		"score": 3
	}, {
		"degree": "稍受限",
		"score": 4
	}, {
		"degree": "不受限",
		"score": 5
	}, {
		"degree": "因其它原因受限",
		"score": 6
	}]
}, {
	"id": 10,
	"type": "selection",
	"title": "与1个月前比较，作最大强度的活动时，胸痛、胸部紧榨感和心绞痛的发作情况",
	"category": "survey",
	"key": "SAQ",
	"option": [{
		"degree": "明显增加",
		"score": 1
	}, {
		"degree": "轻微增加",
		"score": 2
	}, {
		"degree": "相同",
		"score": 3
	}, {
		"degree": "轻微减少",
		"score": 4
	}, {
		"degree": "明显减少",
		"score": 5
	}]
}, {
	"id": 11,
	"type": "selection",
	"title": "过去1个月内，胸痛、胸部紧榨感和心绞痛的平均发作次数",
	"category": "survey",
	"key": "SAQ",
	"option": [{
		"degree": "多于或等于4次/天",
		"score": 1
	}, {
		"degree": "1~3次/天",
		"score": 2
	}, {
		"degree": "多于或等于3次/周",
		"score": 3
	}, {
		"degree": "1~2次/周",
		"score": 4
	}, {
		"degree": "少于1次/周",
		"score": 5
	}, {
		"degree": "无发作",
		"score": 6
	}]
}, {
	"id": 12,
	"type": "selection",
	"title": "过去1个月内，胸痛、胸部紧榨感和心绞痛服用硝基药物(如硝酸甘油)平均次数",
	"category": "survey",
	"key": "SAQ",
	"option": [{
		"degree": "多于或等于4次/天",
		"score": 1
	}, {
		"degree": "1~3次/天",
		"score": 2
	}, {
		"degree": "多于或等于3次/周",
		"score": 3
	}, {
		"degree": "1~2次/周",
		"score": 4
	}, {
		"degree": "少于1次/周",
		"score": 5
	}, {
		"degree": "没使用",
		"score": 6
	}]
}, {
	"id": 13,
	"type": "selection",
	"title": "因胸痛、胸部紧榨感和心绞痛遵守医嘱服药带来的烦恼",
	"category": "survey",
	"key": "SAQ",
	"option": [{
		"degree": "严重",
		"score": 1
	}, {
		"degree": "中度",
		"score": 2
	}, {
		"degree": "轻微",
		"score": 3
	}, {
		"degree": "极少",
		"score": 4
	}, {
		"degree": "无",
		"score": 5
	}, {
		"degree": "医生未给药",
		"score": 6
	}]
}, {
	"id": 14,
	"type": "selection",
	"title": "对治疗胸痛、胸部紧榨感和心绞痛的各种措施的满意程度",
	"category": "survey",
	"key": "SAQ",
	"option": [{
		"degree": "不满意",
		"score": 1
	}, {
		"degree": "大部分不满意",
		"score": 2
	}, {
		"degree": "部分满意",
		"score": 3
	}, {
		"degree": "大部分满意",
		"score": 4
	}, {
		"degree": "高度满意",
		"score": 5
	}]
}, {
	"id": 15,
	"type": "selection",
	"title": "对医生就胸痛、胸部紧榨感和心绞痛的解释满意程度",
	"category": "survey",
	"key": "SAQ",
	"option": [{
		"degree": "不满意",
		"score": 1
	}, {
		"degree": "大部分不满意",
		"score": 2
	}, {
		"degree": "部分满意",
		"score": 3
	}, {
		"degree": "大部分满意",
		"score": 4
	}, {
		"degree": "高度满意",
		"score": 5
	}]
}, {
	"id": 16,
	"type": "selection",
	"title": "总的来说，对目前胸痛、胸部紧榨感和心绞痛的治疗满意程度",
	"category": "survey",
	"key": "SAQ",
	"option": [{
		"degree": "不满意",
		"score": 1
	}, {
		"degree": "大部分不满意",
		"score": 2
	}, {
		"degree": "部分满意",
		"score": 3
	}, {
		"degree": "大部分满意",
		"score": 4
	}, {
		"degree": "高度满意",
		"score": 5
	}]
}, {
	"id": 17,
	"type": "selection",
	"title": "过去4周内，胸痛、胸部紧榨感和心绞痛影响生活乐趣的程度",
	"category": "survey",
	"key": "SAQ",
	"option": [{
		"degree": "不满意",
		"score": 1
	}, {
		"degree": "大部分不满意",
		"score": 2
	}, {
		"degree": "部分满意",
		"score": 3
	}, {
		"degree": "大部分满意",
		"score": 4
	}, {
		"degree": "高度满意",
		"score": 5
	}]
}, {
	"id": 18,
	"type": "selection",
	"title": "在您的未来生活中如果还有胸痛、胸部紧榨感和心绞痛，您会感觉怎样",
	"category": "survey",
	"key": "SAQ",
	"option": [{
		"degree": "不满意",
		"score": 1
	}, {
		"degree": "大部分不满意",
		"score": 2
	}, {
		"degree": "部分满意",
		"score": 3
	}, {
		"degree": "大部分满意",
		"score": 4
	}, {
		"degree": "高度满意",
		"score": 5
	}]
}, {
	"id": 19,
	"type": "selection",
	"title": "对心脏病发作和突然死亡的担心程度",
	"category": "survey",
	"key": "SAQ",
	"option": [{
		"degree": "一直担心",
		"score": 1
	}, {
		"degree": "经常担心",
		"score": 2
	}, {
		"degree": "有时担心",
		"score": 3
	}, {
		"degree": "很少担心",
		"score": 4
	}, {
		"degree": "绝不担心",
		"score": 5
	}]
}, {
	"id": 20,
	"type": "selection",
	"title": "总体而言，你认为你的健康状况如何？",
	"category": "survey",
	"key": "SF-12",
	"option": [{
		"degree": "极好",
		"score": 1
	}, {
		"degree": "非常好",
		"score": 2
	}, {
		"degree": "好",
		"score": 3
	}, {
		"degree": "相当不错",
		"score": 4
	}, {
		"degree": "差",
		"score": 5
	}]
}, {
	"id": 21,
	"type": "selection",
	"title": "这些活动对你的健康状况有影响吗？诸如搬桌子、搞卫生、耕地、打保龄球或高尔夫球。",
	"category": "survey",
	"key": "SF-12",
	"option": [{
		"degree": "限制很多",
		"score": 1
	}, {
		"degree": "限制一点",
		"score": 2
	}, {
		"degree": "一点也没限制",
		"score": 3
	}]
}, {
	"id": 22,
	"type": "selection",
	"title": "爬几段楼梯，现在对你的健康状况有限制吗？",
	"category": "survey",
	"key": "SF-12",
	"option": [{
		"degree": "限制很多",
		"score": 1
	}, {
		"degree": "限制一点",
		"score": 2
	}, {
		"degree": "一点也没限制",
		"score": 3
	}]
}, {
	"id": 23,
	"type": "selection",
	"title": "在过去1个月，由于身体原因，有多少时间是你不能完成你想做的工作或日常活动？",
	"category": "survey",
	"key": "SF-12",
	"option": [{
		"degree": "所有时间",
		"score": 1
	}, {
		"degree": "大多数时间",
		"score": 2
	}, {
		"degree": "有时",
		"score": 3
	}, {
		"degree": "很少时间",
		"score": 4
	}, {
		"degree": "几乎没有",
		"score": 5
	}]
}, {
	"id": 24,
	"type": "selection",
	"title": "在过去1个月，由于身体原因，有多少时间是你做工作或日常活动不如平时仔细？",
	"category": "survey",
	"key": "SF-12",
	"option": [{
		"degree": "所有时间",
		"score": 1
	}, {
		"degree": "大多数时间",
		"score": 2
	}, {
		"degree": "有时",
		"score": 3
	}, {
		"degree": "很少时间",
		"score": 4
	}, {
		"degree": "几乎没有",
		"score": 5
	}]
}, {
	"id": 25,
	"type": "selection",
	"title": "在过去1个月，由于情感原因（如焦虑或心情差），有多少时间是你不能完成你想做的工作或日常活动？",
	"category": "survey",
	"key": "SF-12",
	"option": [{
		"degree": "所有时间",
		"score": 1
	}, {
		"degree": "大多数时间",
		"score": 2
	}, {
		"degree": "有时",
		"score": 3
	}, {
		"degree": "很少时间",
		"score": 4
	}, {
		"degree": "几乎没有",
		"score": 5
	}]
}, {
	"id": 26,
	"type": "selection",
	"title": "在过去1个月，由于情感原因（如焦虑或心情差），有多少时间是你做工作或日常活动不如平时仔细？",
	"category": "survey",
	"key": "SF-12",
	"option": [{
		"degree": "所有时间",
		"score": 1
	}, {
		"degree": "大多数时间",
		"score": 2
	}, {
		"degree": "有时",
		"score": 3
	}, {
		"degree": "很少时间",
		"score": 4
	}, {
		"degree": "几乎没有",
		"score": 5
	}]
}, {
	"id": 27,
	"type": "selection",
	"title": "在过去1个月，疼痛在多大程度上妨碍你的正常工作及家务劳动？",
	"category": "survey",
	"key": "SF-12",
	"option": [{
		"degree": "不影响",
		"score": 1
	}, {
		"degree": "一点点影响",
		"score": 2
	}, {
		"degree": "中度影响",
		"score": 3
	}, {
		"degree": "很大程度影响",
		"score": 4
	}, {
		"degree": "极度影响",
		"score": 5
	}]
}, {
	"id": 28,
	"type": "selection",
	"title": "在过去1个月，你感觉有多长时间是平静的？",
	"category": "survey",
	"key": "SF-12",
	"option": [{
		"degree": "所有时间",
		"score": 1
	}, {
		"degree": "大多数时间",
		"score": 2
	}, {
		"degree": "有时",
		"score": 3
	}, {
		"degree": "很少时间",
		"score": 4
	}, {
		"degree": "几乎没有",
		"score": 5
	}]
}, {
	"id": 29,
	"type": "selection",
	"title": "在过去1个月，你有多长时间是精力充沛的？",
	"category": "survey",
	"key": "SF-12",
	"option": [{
		"degree": "所有时间",
		"score": 1
	}, {
		"degree": "大多数时间",
		"score": 2
	}, {
		"degree": "有时",
		"score": 3
	}, {
		"degree": "很少时间",
		"score": 4
	}, {
		"degree": "几乎没有",
		"score": 5
	}]
}, {
	"id": 30,
	"type": "selection",
	"title": "在过去1个月，你有多长时间感觉心灰意冷？",
	"category": "survey",
	"key": "SF-12",
	"option": [{
		"degree": "所有时间",
		"score": 1
	}, {
		"degree": "大多数时间",
		"score": 2
	}, {
		"degree": "有时",
		"score": 3
	}, {
		"degree": "很少时间",
		"score": 4
	}, {
		"degree": "几乎没有",
		"score": 5
	}]
}, {
	"id": 31,
	"type": "selection",
	"title": "在过去1个月，你的健康状况或情感问题有多长时间影响了你的社交活动（例如访友，探亲等）？",
	"category": "survey",
	"key": "SF-12",
	"option": [{
		"degree": "所有时间",
		"score": 1
	}, {
		"degree": "大多数时间",
		"score": 2
	}, {
		"degree": "有时",
		"score": 3
	}, {
		"degree": "很少时间",
		"score": 4
	}, {
		"degree": "几乎没有",
		"score": 5
	}]
}, {
	"id": 32,
	"type": "selection",
	"title": "在过去的两周里，你生活中出现“做事时提不起劲或没有兴趣”的频率有多少？",
	"category": "survey",
	"key": "PHQ-9",
	"option": [{
		"degree": "没有",
		"score": 0
	}, {
		"degree": "有几天",
		"score": 1
	}, {
		"degree": "一半以上时间",
		"score": 2
	}, {
		"degree": "几乎天天",
		"score": 3
	}]
}, {
	"id": 33,
	"type": "selection",
	"title": "在过去的两周里，你生活中出现“感到心情低落, 沮丧或绝望”的频率有多少？",
	"category": "survey",
	"key": "PHQ-9",
	"option": [{
		"degree": "没有",
		"score": 0
	}, {
		"degree": "有几天",
		"score": 1
	}, {
		"degree": "一半以上时间",
		"score": 2
	}, {
		"degree": "几乎天天",
		"score": 3
	}]
}, {
	"id": 34,
	"type": "selection",
	"title": "在过去的两周里，你生活中出现“入睡困难、睡不安或睡得过多”的频率有多少？",
	"category": "survey",
	"key": "PHQ-9",
	"option": [{
		"degree": "没有",
		"score": 0
	}, {
		"degree": "有几天",
		"score": 1
	}, {
		"degree": "一半以上时间",
		"score": 2
	}, {
		"degree": "几乎天天",
		"score": 3
	}]
}, {
	"id": 35,
	"type": "selection",
	"title": "在过去的两周里，你生活中出现“感觉疲倦或没有活力”的频率有多少？",
	"category": "survey",
	"key": "PHQ-9",
	"option": [{
		"degree": "没有",
		"score": 0
	}, {
		"degree": "有几天",
		"score": 1
	}, {
		"degree": "一半以上时间",
		"score": 2
	}, {
		"degree": "几乎天天",
		"score": 3
	}]
}, {
	"id": 36,
	"type": "selection",
	"title": "在过去的两周里，你生活中出现“食欲不振或吃太多”的频率有多少？",
	"category": "survey",
	"key": "PHQ-9",
	"option": [{
		"degree": "没有",
		"score": 0
	}, {
		"degree": "有几天",
		"score": 1
	}, {
		"degree": "一半以上时间",
		"score": 2
	}, {
		"degree": "几乎天天",
		"score": 3
	}]
}, {
	"id": 37,
	"type": "selection",
	"title": "在过去的两周里，你生活中出现“觉得自己很糟或觉得自己很失败，或让自己、家人失望”的频率有多少？",
	"category": "survey",
	"key": "PHQ-9",
	"option": [{
		"degree": "没有",
		"score": 0
	}, {
		"degree": "有几天",
		"score": 1
	}, {
		"degree": "一半以上时间",
		"score": 2
	}, {
		"degree": "几乎天天",
		"score": 3
	}]
}, {
	"id": 38,
	"type": "selection",
	"title": "在过去的两周里，你生活中出现“对事物专注有困难，例如看报纸或看电视时”的频率有多少？",
	"category": "survey",
	"key": "PHQ-9",
	"option": [{
		"degree": "没有",
		"score": 0
	}, {
		"degree": "有几天",
		"score": 1
	}, {
		"degree": "一半以上时间",
		"score": 2
	}, {
		"degree": "几乎天天",
		"score": 3
	}]
}, {
	"id": 39,
	"type": "selection",
	"title": "在过去的两周里，你生活中出现“行动或说话速度缓慢到别人已经察觉？或刚好相反——变得比平日更烦躁或坐立不安，动来动去”的频率有多少？",
	"category": "survey",
	"key": "PHQ-9",
	"option": [{
		"degree": "没有",
		"score": 0
	}, {
		"degree": "有几天",
		"score": 1
	}, {
		"degree": "一半以上时间",
		"score": 2
	}, {
		"degree": "几乎天天",
		"score": 3
	}]
}, {
	"id": 40,
	"type": "selection",
	"title": "在过去的两周里，你生活中出现“有不如死掉或用某种方式伤害自己的念头”的频率有多少？",
	"category": "survey",
	"key": "PHQ-9",
	"option": [{
		"degree": "没有",
		"score": 0
	}, {
		"degree": "有几天",
		"score": 1
	}, {
		"degree": "一半以上时间",
		"score": 2
	}, {
		"degree": "几乎天天",
		"score": 3
	}]
}, {
	"id": 41,
	"type": "selection",
	"title": "目前的活动能力",
	"category": "survey",
	"key": "EQ-5D",
	"option": [{
		"degree": "走路没问题",
		"score": 1
	}, {
		"degree": "走路有些问题",
		"score": 2
	}, {
		"degree": "卧床不起",
		"score": 3
	}]
}, {
	"id": 42,
	"type": "selection",
	"title": "目前的自理能力",
	"category": "survey",
	"key": "EQ-5D",
	"option": [{
		"degree": "可以完全自理",
		"score": 1
	}, {
		"degree": "洗澡或穿衣服有些问题",
		"score": 2
	}, {
		"degree": "无法自己洗澡或穿衣服",
		"score": 3
	}]
}, {
	"id": 43,
	"type": "selection",
	"title": "目前的日常活动能力(如，工作、学习、家务、家庭或闲暇活动)",
	"category": "survey",
	"key": "EQ-5D",
	"option": [{
		"degree": "进行日常活动没有问题",
		"score": 1
	}, {
		"degree": "进行日常活动有些问题",
		"score": 2
	}, {
		"degree": "无法进行日常活动",
		"score": 3
	}]
}, {
	"id": 44,
	"type": "selection",
	"title": "目前的疼痛或不舒适情况",
	"category": "survey",
	"key": "EQ-5D",
	"option": [{
		"degree": "没有疼痛或不舒适",
		"score": 1
	}, {
		"degree": "有中度疼痛或不舒适",
		"score": 2
	}, {
		"degree": "极度疼痛或不舒适",
		"score": 3
	}]
}, {
	"id": 45,
	"type": "selection",
	"title": "目前的焦虑或抑郁情况",
	"category": "survey",
	"key": "EQ-5D",
	"option": [{
		"degree": "不焦虑或抑郁",
		"score": 1
	}, {
		"degree": "轻度焦虑或抑郁",
		"score": 2
	}, {
		"degree": "中度焦虑或抑郁",
		"score": 3
	}]
}, {
	"id": 46,
  "type": "input",
	"title": "目前的健康状况(0-100分)",
	"category": "survey",
	"key": "EQ-5D",
  "option": null
}]